setup.cfg
setup.py
cleave/__init__.py
cleave/encrypt.py
cleave/server.py
cleave.egg-info/PKG-INFO
cleave.egg-info/SOURCES.txt
cleave.egg-info/dependency_links.txt
cleave.egg-info/entry_points.txt
cleave.egg-info/top_level.txt
cleave/debug/__init__.py
cleave/http/__init__.py
cleave/http/handler.py
cleave/http/request.py
cleave/http/response.py
cleave/http/status.py
cleave/tool/__init__.py
cleave/tool/serve.py