Metadata-Version: 1.1
Name: cleave
Version: 0.27
Summary: Python easy tools library. Allows to run local http server in one command.
Home-page: https://github.com/Max201/cleave
Author: Maxim Papezhuk
Author-email: maxp.job@gmail.com
License: UNKNOWN
Download-URL: https://github.com/Max201/cleave/tarball/v0.27
Keywords: server,python,socket,easy,encryption,http server,file server
Platform: UNKNOWN
